flacfetch/__init__.py
flacfetch/api/__init__.py
flacfetch/api/auth.py
flacfetch/api/main.py
flacfetch/api/models.py
flacfetch/api/routes/__init__.py
flacfetch/api/routes/cache.py
flacfetch/api/routes/config.py
flacfetch/api/routes/credentials.py
flacfetch/api/routes/download.py
flacfetch/api/routes/health.py
flacfetch/api/routes/search.py
flacfetch/api/routes/torrents.py
flacfetch/api/services/__init__.py
flacfetch/api/services/credential_check.py
flacfetch/api/services/disk_manager.py
flacfetch/api/services/download_manager.py
flacfetch/api/services/health_check.py
flacfetch/api/services/search_cache.py
flacfetch/core/categorize.py
flacfetch/core/config.py
flacfetch/core/interfaces.py
flacfetch/core/log.py
flacfetch/core/manager.py
flacfetch/core/matching.py
flacfetch/core/models.py
flacfetch/downloaders/spotify.py
flacfetch/downloaders/torrent.py
flacfetch/downloaders/youtube.py
flacfetch/interface/cli.py
flacfetch/interface/cli_remote.py
flacfetch/providers/gazelle.py
flacfetch/providers/ops.py
flacfetch/providers/red.py
flacfetch/providers/spotify.py
flacfetch/providers/youtube.py
flacfetch-0.18.0.dist-info/licenses/LICENSE
flacfetch-0.18.0.dist-info/METADATA
flacfetch-0.18.0.dist-info/WHEEL
flacfetch-0.18.0.dist-info/entry_points.txt
flacfetch-0.18.0.dist-info/top_level.txt
flacfetch-0.18.0.dist-info/RECORD
