Metadata-Version: 2.4
Name: flacfetch
Version: 0.18.0
Summary: Search and download high-quality audio from multiple sources
Home-page: https://github.com/yourusername/flacfetch
Author: Your Name
Author-email: Andrew Beveridge <andrew@beveridge.uk>
License-Expression: MIT
Project-URL: Homepage, https://github.com/nomadkaraoke/flacfetch
Project-URL: Repository, https://github.com/nomadkaraoke/flacfetch
Project-URL: Issues, https://github.com/nomadkaraoke/flacfetch/issues
Keywords: audio,music,flac,download,youtube,torrent
Classifier: Development Status :: 4 - Beta
Classifier: Intended Audience :: End Users/Desktop
Classifier: Operating System :: OS Independent
Classifier: Programming Language :: Python :: 3
Classifier: Programming Language :: Python :: 3.10
Classifier: Programming Language :: Python :: 3.11
Classifier: Programming Language :: Python :: 3.12
Classifier: Programming Language :: Python :: 3.13
Classifier: Topic :: Multimedia :: Sound/Audio
Classifier: Environment :: Console
Requires-Python: >=3.8
License-File: LICENSE
Requires-Dist: requests>=2.28.0
Requires-Dist: yt-dlp>=2023.0.0
Requires-Dist: transmission-rpc>=7.0.0
Provides-Extra: remote
Requires-Dist: httpx>=0.28.0; extra == "remote"
Requires-Dist: playwright>=1.40.0; extra == "remote"
Provides-Extra: api
Requires-Dist: fastapi>=0.115.0; extra == "api"
Requires-Dist: uvicorn[standard]>=0.24.0; extra == "api"
Requires-Dist: pydantic>=2.0.0; extra == "api"
Requires-Dist: httpx>=0.28.0; extra == "api"
Requires-Dist: google-cloud-storage>=2.13.0; extra == "api"
Requires-Dist: google-cloud-secret-manager>=2.16.0; extra == "api"
Provides-Extra: spotify
Requires-Dist: spotipy>=2.25.1; extra == "spotify"
Provides-Extra: ejs
Requires-Dist: yt-dlp-ejs>=0.3.0; extra == "ejs"
Provides-Extra: dev
Requires-Dist: pytest>=7.0.0; extra == "dev"
Requires-Dist: pytest-mock>=3.10.0; extra == "dev"
Requires-Dist: pytest-cov>=4.0.0; extra == "dev"
Requires-Dist: pytest-asyncio>=0.23.0; extra == "dev"
Requires-Dist: ruff>=0.1.0; extra == "dev"
Requires-Dist: mypy>=1.0.0; extra == "dev"
Requires-Dist: types-requests>=2.28.0; extra == "dev"
Provides-Extra: all
Requires-Dist: httpx>=0.28.0; extra == "all"
Requires-Dist: playwright>=1.40.0; extra == "all"
Requires-Dist: fastapi>=0.115.0; extra == "all"
Requires-Dist: uvicorn[standard]>=0.24.0; extra == "all"
Requires-Dist: pydantic>=2.0.0; extra == "all"
Requires-Dist: google-cloud-storage>=2.13.0; extra == "all"
Requires-Dist: google-cloud-secret-manager>=2.16.0; extra == "all"
Requires-Dist: spotipy>=2.25.1; extra == "all"
Requires-Dist: yt-dlp-ejs>=0.3.0; extra == "all"
Requires-Dist: pytest>=7.0.0; extra == "all"
Requires-Dist: pytest-mock>=3.10.0; extra == "all"
Requires-Dist: pytest-cov>=4.0.0; extra == "all"
Requires-Dist: pytest-asyncio>=0.23.0; extra == "all"
Requires-Dist: ruff>=0.1.0; extra == "all"
Requires-Dist: mypy>=1.0.0; extra == "all"
Requires-Dist: types-requests>=2.28.0; extra == "all"
Dynamic: author
Dynamic: home-page
Dynamic: license-file
Dynamic: requires-python
